biosaur2/__init__.py
biosaur2/cutils.cp310-win_amd64.pyd
biosaur2/main.py
biosaur2/main_dia.py
biosaur2/search.py
biosaur2/utils.py
biosaur2-0.2.213.dist-info/LICENSE
biosaur2-0.2.213.dist-info/METADATA
biosaur2-0.2.213.dist-info/WHEEL
biosaur2-0.2.213.dist-info/entry_points.txt
biosaur2-0.2.213.dist-info/top_level.txt
biosaur2-0.2.213.dist-info/RECORD
