Metadata-Version: 2.1
Name: biosaur2
Version: 0.2.213
Summary: A feature detection LC-MS1 spectra.
Author: Mark Ivanov
Author-email: markmipt@gmail.com
License: License :: OSI Approved :: Apache Software License
Classifier: Intended Audience :: Science/Research
Classifier: Programming Language :: Python :: 3.9
Classifier: Topic :: Education
Classifier: Topic :: Scientific/Engineering :: Bio-Informatics
Classifier: Topic :: Scientific/Engineering :: Chemistry
Classifier: Topic :: Scientific/Engineering :: Physics
License-File: LICENSE
Requires-Dist: pyteomics
Requires-Dist: scipy
Requires-Dist: numpy
Requires-Dist: pandas
Requires-Dist: lxml
Requires-Dist: cython
Requires-Dist: setuptools
